LICENSE.txt
MANIFEST
setup.py
src/davclient/__init__.py
src/davclient/davclient.py
src/davclient.egg-info/PKG-INFO
src/davclient.egg-info/SOURCES.txt
src/davclient.egg-info/dependency_links.txt
src/davclient.egg-info/top_level.txt
