Metadata-Version: 1.0
Name: davclient
Version: 0.2.0
Summary: Simple WebDAV client.
Home-page: http://wiki.osafoundation.org/Projects/Davclient
Author: Open Source Applications Foundation
Author-email: tools-dev@osafoundation.org
License: http://www.apache.org/licenses/LICENSE-2.0
Platform: Any
Classifier: Development Status :: 4 - Beta
Classifier: Environment :: Console
Classifier: Intended Audience :: Developers
Classifier: License :: OSI Approved :: Apache Software License
Classifier: Operating System :: OS Independent
Classifier: Topic :: Software Development :: Libraries :: Python Modules
